{
  "caseId": "a8461b54-c952-4612-bfbe-881b74bef130",
  "filingNumber": "KL-002070-2025",
  "nayamitraAuthToken": "4cd312bd-6d2e-4d45-b6c2-922c83af20bd",
  "fsousername": "michaelGeorgeFso",
  "fsopassword": "Beehyv@123",
  "fsoauthtoken": "33432ef4-1189-475b-974d-9da1160f40f5",
  "judgeusername": "michaelGeorgeJudge",
  "judgepassword": "Beehyv@123",
  "judgeauthtoken": "928f2ec3-adc0-4264-95fc-931ba0b5ceb8",
  "cnrNumber": "KLKM520007382025",
  "orderId": "e5f1fcba-2563-4cda-be0c-e24bd233db85",
  "orderNumber": "KL-002061-2025-OR1",
  "hearingId": "KL-002061-2025-HR1",
  "citizenUserInfo": {
    "id": 2149,
    "uuid": "5426acd3-e73f-458c-bfeb-2819a4caa0fd",
    "userName": "8826000000",
    "name": "ADV EIGHT TWENTY SIX  ",
    "mobileNumber": "8826000000",
    "emailId": "test26@gmail.com",
    "locale": null,
    "type": "CITIZEN",
    "roles": [
      {
        "name": "USER_REGISTER",
        "code": "USER_REGISTER",
        "tenantId": "kl"
      },
      {
        "name": "CASE_VIEWER",
        "code": "CASE_VIEWER",
        "tenantId": "kl"
      },
      {
        "name": "HEARING_VIEWER",
        "code": "HEARING_VIEWER",
        "tenantId": "kl"
      },
      {
        "name": "Citizen",
        "code": "CITIZEN",
        "tenantId": "kl"
      },
      {
        "name": "ADVOCATE_ROLE",
        "code": "ADVOCATE_ROLE",
        "tenantId": "kl"
      },
      {
        "name": "APPLICATION_CREATOR",
        "code": "APPLICATION_CREATOR",
        "tenantId": "kl"
      },
      {
        "name": "EVIDENCE_CREATOR",
        "code": "EVIDENCE_CREATOR",
        "tenantId": "kl"
      },
      {
        "name": "EVIDENCE_EDITOR",
        "code": "EVIDENCE_EDITOR",
        "tenantId": "kl"
      },
      {
        "name": "SUBMISSION_DELETE",
        "code": "SUBMISSION_DELETE",
        "tenantId": "kl"
      },
      {
        "name": "HEARING_ACCEPTOR",
        "code": "HEARING_ACCEPTOR",
        "tenantId": "kl"
      },
      {
        "name": "ORDER_VIEWER",
        "code": "ORDER_VIEWER",
        "tenantId": "kl"
      },
      {
        "name": "SUBMISSION_RESPONDER",
        "code": "SUBMISSION_RESPONDER",
        "tenantId": "kl"
      },
      {
        "name": "CASE_EDITOR",
        "code": "CASE_EDITOR",
        "tenantId": "kl"
      },
      {
        "name": "EVIDENCE_VIEWER",
        "code": "EVIDENCE_VIEWER",
        "tenantId": "kl"
      },
      {
        "name": "ADVOCATE_VIEWER",
        "code": "ADVOCATE_VIEWER",
        "tenantId": "kl"
      },
      {
        "name": "APPLICATION_VIEWER",
        "code": "APPLICATION_VIEWER",
        "tenantId": "kl"
      },
      {
        "name": "SUBMISSION_CREATOR",
        "code": "SUBMISSION_CREATOR",
        "tenantId": "kl"
      },
      {
        "name": "TASK_VIEWER",
        "code": "TASK_VIEWER",
        "tenantId": "kl"
      },
      {
        "name": "ADVOCATE_APPLICATION_VIEWER",
        "code": "ADVOCATE_APPLICATION_VIEWER",
        "tenantId": "kl"
      },
      {
        "name": "CASE_CREATOR",
        "code": "CASE_CREATOR",
        "tenantId": "kl"
      },
      {
        "name": "PENDING_TASK_CREATOR",
        "code": "PENDING_TASK_CREATOR",
        "tenantId": "kl"
      }
    ],
    "active": true,
    "tenantId": "kl",
    "permanentCity": null
  },
  "applicationId": "6c862d86-aab6-4298-b469-3e4af834f5d0",
  "applicationNumber": "KL-002061-2025-AP1",
  "applicationCreatedDate": 1752066924567,
  "statuteSectionId": "b570824a-3e03-4671-b1f0-8d61d2b5b6ef",
  "applicationDocumentId": "4bbf8f4b-3816-4f03-abf5-ffef36b11c0e",
  "applicationDocumentFileStore": "78abb8bd-c5e0-4cb1-9818-48425f10615a",
  "demandId": "f7ea7d1b-391a-4066-a322-d56a53134982",
  "billId": "a0db200e-bd38-47be-8927-8cb24b2e2c17",
  "citizenAuthToken": "1e288cbd-ebfb-4ab3-96a1-ba2d91b770a4",
  "epochTime": 1752128489577,
  "representingid": "e359be37-148a-4822-b425-285bab678b67",
  "litigantid": "ce07e212-59f5-494b-ab5a-14d63daf4456",
  "representingli": "6a45b858-ab9f-4da2-ba68-9577e729ab97",
  "artifactId": "28c76f25-966e-4ab8-a252-f36b0fb1594f",
  "artifactNumber": "KL-002061-2025-AR6",
  "baseURL": "https://dristi-kerala-uat.pucar.org/",
  "advocateId": "1e641bf6-14d9-43d6-b6d9-5632406dd77e",
  "advocateuserUUID": "5426acd3-e73f-458c-bfeb-2819a4caa0fd",
  "advocateIndividualId": "IND-2025-06-27-000443"
}