{
  "baseURL": "https://dristi-kerala-uat.pucar.org/",
  "caseId": "842aae27-a3b9-43ab-9fe4-682ccc7ddcce",
  "filingNumber": "KL-002208-2025",
  "nayamitraAuthToken": "4b5a1e5c-5277-4df2-b048-d576aab6e3e5",
  "fsousername": "michaelGeorgeFso",
  "fsopassword": "Beehyv@123",
  "judgeusername": "michaelGeorgeJudge",
  "judgepassword": "Beehyv@123",
  "judgeauthtoken": "242ae894-a6ac-4760-8ba5-92e89b1c80ec",
  "cnrNumber": "KLKM520011912025",
  "orderId": "ac854c53-9743-404f-ad1e-8ab9b04044dc",
  "orderNumber": "KL-002204-2025-OR1",
  "hearingId": "KL-002204-2025-HR1",
  "applicationId": "b120f3ea-fbcf-42e3-989e-7fbe68b3d651",
  "applicationNumber": "KL-002204-2025-AP1",
  "applicationCreatedDate": 1753105779949,
  "statuteSectionId": "22c92c84-475e-4929-95a3-7590ae4a7a0a",
  "applicationDocumentId": "e291aa3c-6142-4e14-8a36-57b38c52007c",
  "applicationDocumentFileStore": "f700e0c3-b6d2-4beb-bb07-a748aab5ca35",
  "advocateuserUUID": "0e981cc9-1c0c-4409-9850-131f79128862",
  "advocateIndividualId": "IND-2025-05-09-000306",
  "demandId": "d9c39b35-c0d8-4974-b8c6-58ffb7544e17",
  "billId": "e09ea5ad-a3db-46bb-8672-ae255f94e15a",
  "epochTime": 1753192876765,
  "representingid": "76d3a8a2-df6d-4c51-82d7-e3b7e8e7d66d",
  "litigantid": "ca4576a2-fffa-4e29-9396-748380eb5bf7",
  "representingli": "9c2cfb2c-6b45-4464-a37e-d394781f3bea",
  "artifactId": "abd2ce0b-cf88-4a1b-beaf-d607606d3849",
  "artifactNumber": "KL-002204-2025-AR6",
  "advocateId": "1ba92005-67de-45d9-a54e-8d388dce4969",
  "nayamitraUserResponse": {
    "access_token": "4b5a1e5c-5277-4df2-b048-d576aab6e3e5",
    "token_type": "bearer",
    "refresh_token": "f33e533f-441c-4a6f-ae2c-3855bbee55d4",
    "expires_in": 604435,
    "scope": "read",
    "ResponseInfo": {
      "api_id": "",
      "ver": "",
      "ts": "",
      "res_msg_id": "",
      "msg_id": "",
      "status": "Access Token generated successfully"
    },
    "UserRequest": {
      "id": 2125,
      "uuid": "c04ed0f9-03de-41b2-84a8-bfe8535a5d60",
      "userName": "michaelGeorgeNm",
      "name": "michaelGeorgeNm",
      "mobileNumber": "9743294383",
      "emailId": "michaelGeorgeNm@gmail.com",
      "locale": null,
      "type": "EMPLOYEE",
      "roles": [
        {
          "name": "ADVOCATE_CLERK_APPROVER",
          "code": "ADVOCATE_CLERK_APPROVER",
          "tenantId": "kl"
        },
        {
          "name": "PAYMENT_COLLECTOR",
          "code": "PAYMENT_COLLECTOR",
          "tenantId": "kl"
        },
        {
          "name": "ORDER_VIEWER",
          "code": "ORDER_VIEWER",
          "tenantId": "kl"
        },
        {
          "name": "NYAY_MITRA_ROLE",
          "code": "NYAY_MITRA_ROLE",
          "tenantId": "kl"
        },
        {
          "name": "Employee",
          "code": "EMPLOYEE",
          "tenantId": "kl"
        },
        {
          "name": "ADVOCATE_APPROVER",
          "code": "ADVOCATE_APPROVER",
          "tenantId": "kl"
        },
        {
          "name": "ADVOCATE_APPLICATION_VIEWER",
          "code": "ADVOCATE_APPLICATION_VIEWER",
          "tenantId": "kl"
        },
        {
          "name": "TASK_VIEWER",
          "code": "TASK_VIEWER",
          "tenantId": "kl"
        }
      ],
      "active": true,
      "tenantId": "kl",
      "permanentCity": null
    }
  },
  "fsoUserResponse": {
    "access_token": "c6711b99-ced7-4999-987c-2c0d9947ec62",
    "token_type": "bearer",
    "refresh_token": "58843ffa-4a77-423c-b0ee-102c51bbd70f",
    "expires_in": 604434,
    "scope": "read",
    "ResponseInfo": {
      "api_id": "",
      "ver": "",
      "ts": "",
      "res_msg_id": "",
      "msg_id": "",
      "status": "Access Token generated successfully"
    },
    "UserRequest": {
      "id": 2122,
      "uuid": "9e54367b-057a-4c51-8eba-578ae12478a5",
      "userName": "michaelGeorgeFso",
      "name": "michaelGeorgeFso",
      "mobileNumber": "9394534754",
      "emailId": "michaelGeorgeFso@gmail.com",
      "locale": null,
      "type": "EMPLOYEE",
      "roles": [
        {
          "name": "FSO_ROLE",
          "code": "FSO_ROLE",
          "tenantId": "kl"
        },
        {
          "name": "CASE_VIEWER",
          "code": "CASE_VIEWER",
          "tenantId": "kl"
        },
        {
          "name": "HEARING_VIEWER",
          "code": "HEARING_VIEWER",
          "tenantId": "kl"
        },
        {
          "name": "HEARING_APPROVER",
          "code": "HEARING_APPROVER",
          "tenantId": "kl"
        },
        {
          "name": "CASE_REVIEWER",
          "code": "CASE_REVIEWER",
          "tenantId": "kl"
        },
        {
          "name": "ORDER_VIEWER",
          "code": "ORDER_VIEWER",
          "tenantId": "kl"
        },
        {
          "name": "ORDER_REASSIGN",
          "code": "ORDER_REASSIGN",
          "tenantId": "kl"
        },
        {
          "name": "CASE_EDITOR",
          "code": "CASE_EDITOR",
          "tenantId": "kl"
        },
        {
          "name": "ORDER_APPROVER",
          "code": "ORDER_APPROVER",
          "tenantId": "kl"
        },
        {
          "name": "Employee",
          "code": "EMPLOYEE",
          "tenantId": "kl"
        },
        {
          "name": "General Court Room Manager",
          "code": "GENERAL_COURT_ROOM_MANAGER",
          "tenantId": "kl"
        }
      ],
      "active": true,
      "tenantId": "kl",
      "permanentCity": null
    }
  },
  "fsoauthtoken": "c6711b99-ced7-4999-987c-2c0d9947ec62",
  "judgeUserResponse": {
    "access_token": "242ae894-a6ac-4760-8ba5-92e89b1c80ec",
    "token_type": "bearer",
    "refresh_token": "3374b906-f395-46fc-bf68-2b970bb2d268",
    "expires_in": 602821,
    "scope": "read",
    "ResponseInfo": {
      "api_id": "",
      "ver": "",
      "ts": "",
      "res_msg_id": "",
      "msg_id": "",
      "status": "Access Token generated successfully"
    },
    "UserRequest": {
      "id": 1981,
      "uuid": "747a447a-82a8-4b21-9225-6bffc5619d64",
      "userName": "michaelGeorgeJudge",
      "name": "Judge UAT",
      "mobileNumber": "6262626262",
      "emailId": "chrajesh966@gmail.com",
      "locale": null,
      "type": "EMPLOYEE",
      "roles": [
        {
          "name": "DIARY_APPROVER",
          "code": "DIARY_APPROVER",
          "tenantId": "kl"
        },
        {
          "name": "HEARING_VIEWER",
          "code": "HEARING_VIEWER",
          "tenantId": "kl"
        },
        {
          "name": "WORKFLOW_ABANDON",
          "code": "WORKFLOW_ABANDON",
          "tenantId": "kl"
        },
        {
          "name": "ORDER_ESIGN",
          "code": "ORDER_ESIGN",
          "tenantId": "kl"
        },
        {
          "name": "Workflow Admin",
          "code": "WORKFLOW_ADMIN",
          "tenantId": "kl"
        },
        {
          "name": "APPLICATION_CREATOR",
          "code": "APPLICATION_CREATOR",
          "tenantId": "kl"
        },
        {
          "name": "DEPOSITION_PUBLISHER",
          "code": "DEPOSITION_PUBLISHER",
          "tenantId": "kl"
        },
        {
          "name": "HEARING_APPROVER",
          "code": "HEARING_APPROVER",
          "tenantId": "kl"
        },
        {
          "name": "SUBMISSION_RESPONDER",
          "code": "SUBMISSION_RESPONDER",
          "tenantId": "kl"
        },
        {
          "name": "ORDER_VIEWER",
          "code": "ORDER_VIEWER",
          "tenantId": "kl"
        },
        {
          "name": "ORDER_REASSIGN",
          "code": "ORDER_REASSIGN",
          "tenantId": "kl"
        },
        {
          "name": "CASE_EDITOR",
          "code": "CASE_EDITOR",
          "tenantId": "kl"
        },
        {
          "name": "TASK_CREATOR",
          "code": "TASK_CREATOR",
          "tenantId": "kl"
        },
        {
          "name": "APPLICATION_APPROVER",
          "code": "APPLICATION_APPROVER",
          "tenantId": "kl"
        },
        {
          "name": "DIARY_VIEWER",
          "code": "DIARY_VIEWER",
          "tenantId": "kl"
        },
        {
          "name": "Employee",
          "code": "EMPLOYEE",
          "tenantId": "kl"
        },
        {
          "name": "SUBMISSION_CREATOR",
          "code": "SUBMISSION_CREATOR",
          "tenantId": "kl"
        },
        {
          "name": "ORDER_DELETE",
          "code": "ORDER_DELETE",
          "tenantId": "kl"
        },
        {
          "name": "NOTIFICATION_APPROVER",
          "code": "NOTIFICATION_APPROVER",
          "tenantId": "kl"
        },
        {
          "name": "CASE_VIEWER",
          "code": "CASE_VIEWER",
          "tenantId": "kl"
        },
        {
          "name": "PDF_CREATOR",
          "code": "PDF_CREATOR",
          "tenantId": "kl"
        },
        {
          "name": "TASK_EDITOR",
          "code": "TASK_EDITOR",
          "tenantId": "kl"
        },
        {
          "name": "APPLICATION_REJECTOR",
          "code": "APPLICATION_REJECTOR",
          "tenantId": "kl"
        },
        {
          "name": "HEARING_EDITOR",
          "code": "HEARING_EDITOR",
          "tenantId": "kl"
        },
        {
          "name": "BAIL_BOND_VIEWER",
          "code": "BAIL_BOND_VIEWER",
          "tenantId": "kl"
        },
        {
          "name": "ORDER_APPROVER",
          "code": "ORDER_APPROVER",
          "tenantId": "kl"
        },
        {
          "name": "DIARY_EDITOR",
          "code": "DIARY_EDITOR",
          "tenantId": "kl"
        },
        {
          "name": "NOTIFICATION_CREATOR",
          "code": "NOTIFICATION_CREATOR",
          "tenantId": "kl"
        },
        {
          "name": "HEARING_CREATOR",
          "code": "HEARING_CREATOR",
          "tenantId": "kl"
        },
        {
          "name": "ORDER_CREATOR",
          "code": "ORDER_CREATOR",
          "tenantId": "kl"
        },
        {
          "name": "EVIDENCE_CREATOR",
          "code": "EVIDENCE_CREATOR",
          "tenantId": "kl"
        },
        {
          "name": "CALCULATION_VIEWER",
          "code": "CALCULATION_VIEWER",
          "tenantId": "kl"
        },
        {
          "name": "JUDGE_ROLE",
          "code": "JUDGE_ROLE",
          "tenantId": "kl"
        },
        {
          "name": "EVIDENCE_EDITOR",
          "code": "EVIDENCE_EDITOR",
          "tenantId": "kl"
        },
        {
          "name": "CASE_APPROVER",
          "code": "CASE_APPROVER",
          "tenantId": "kl"
        },
        {
          "name": "SUBMISSION_APPROVER",
          "code": "SUBMISSION_APPROVER",
          "tenantId": "kl"
        },
        {
          "name": "TASK_VIEWER",
          "code": "TASK_VIEWER",
          "tenantId": "kl"
        },
        {
          "name": "HEARING_SCHEDULER",
          "code": "HEARING_SCHEDULER",
          "tenantId": "kl"
        },
        {
          "name": "BAIL_BOND_APPROVER",
          "code": "BAIL_BOND_APPROVER",
          "tenantId": "kl"
        }
      ],
      "active": true,
      "tenantId": "kl",
      "permanentCity": null
    }
  },
  "NAYAMITRAuserinfo": {
    "id": 2125,
    "uuid": "c04ed0f9-03de-41b2-84a8-bfe8535a5d60",
    "userName": "michaelGeorgeNm",
    "name": "michaelGeorgeNm",
    "mobileNumber": "9743294383",
    "emailId": "michaelGeorgeNm@gmail.com",
    "locale": null,
    "type": "EMPLOYEE",
    "roles": [
      {
        "name": "ADVOCATE_CLERK_APPROVER",
        "code": "ADVOCATE_CLERK_APPROVER",
        "tenantId": "kl"
      },
      {
        "name": "PAYMENT_COLLECTOR",
        "code": "PAYMENT_COLLECTOR",
        "tenantId": "kl"
      },
      {
        "name": "ORDER_VIEWER",
        "code": "ORDER_VIEWER",
        "tenantId": "kl"
      },
      {
        "name": "NYAY_MITRA_ROLE",
        "code": "NYAY_MITRA_ROLE",
        "tenantId": "kl"
      },
      {
        "name": "Employee",
        "code": "EMPLOYEE",
        "tenantId": "kl"
      },
      {
        "name": "ADVOCATE_APPROVER",
        "code": "ADVOCATE_APPROVER",
        "tenantId": "kl"
      },
      {
        "name": "ADVOCATE_APPLICATION_VIEWER",
        "code": "ADVOCATE_APPLICATION_VIEWER",
        "tenantId": "kl"
      },
      {
        "name": "TASK_VIEWER",
        "code": "TASK_VIEWER",
        "tenantId": "kl"
      }
    ],
    "active": true,
    "tenantId": "kl",
    "permanentCity": null
  },
  "nayamitrauuid": "c04ed0f9-03de-41b2-84a8-bfe8535a5d60",
  "FSOuserinfo": {
    "id": 2122,
    "uuid": "9e54367b-057a-4c51-8eba-578ae12478a5",
    "userName": "michaelGeorgeFso",
    "name": "michaelGeorgeFso",
    "mobileNumber": "9394534754",
    "emailId": "michaelGeorgeFso@gmail.com",
    "locale": null,
    "type": "EMPLOYEE",
    "roles": [
      {
        "name": "FSO_ROLE",
        "code": "FSO_ROLE",
        "tenantId": "kl"
      },
      {
        "name": "CASE_VIEWER",
        "code": "CASE_VIEWER",
        "tenantId": "kl"
      },
      {
        "name": "HEARING_VIEWER",
        "code": "HEARING_VIEWER",
        "tenantId": "kl"
      },
      {
        "name": "HEARING_APPROVER",
        "code": "HEARING_APPROVER",
        "tenantId": "kl"
      },
      {
        "name": "CASE_REVIEWER",
        "code": "CASE_REVIEWER",
        "tenantId": "kl"
      },
      {
        "name": "ORDER_VIEWER",
        "code": "ORDER_VIEWER",
        "tenantId": "kl"
      },
      {
        "name": "ORDER_REASSIGN",
        "code": "ORDER_REASSIGN",
        "tenantId": "kl"
      },
      {
        "name": "CASE_EDITOR",
        "code": "CASE_EDITOR",
        "tenantId": "kl"
      },
      {
        "name": "ORDER_APPROVER",
        "code": "ORDER_APPROVER",
        "tenantId": "kl"
      },
      {
        "name": "Employee",
        "code": "EMPLOYEE",
        "tenantId": "kl"
      },
      {
        "name": "General Court Room Manager",
        "code": "GENERAL_COURT_ROOM_MANAGER",
        "tenantId": "kl"
      }
    ],
    "active": true,
    "tenantId": "kl",
    "permanentCity": null
  },
  "fsouuid": "9e54367b-057a-4c51-8eba-578ae12478a5",
  "litigentAuthToken": "f4ab05d5-2d32-49b1-8e79-936056bd3d8b",
  "litigentuuid": "a9597a93-4e38-49a8-8819-dd8f20bb1f91",
  "litigentIndividualResponse": {
    "ResponseInfo": {
      "apiId": "Rainmaker",
      "ver": null,
      "ts": 1753192883474,
      "resMsgId": "1753192883331|en_IN",
      "msgId": "1753192883331|en_IN",
      "status": "successful"
    },
    "Individual": [
      {
        "id": "f6db2008-4c9d-42ce-8e7c-7761952b74fd",
        "individualId": "IND-2025-05-09-000305",
        "tenantId": "kl",
        "clientReferenceId": null,
        "userId": "1978",
        "userUuid": "a9597a93-4e38-49a8-8819-dd8f20bb1f91",
        "name": {
          "givenName": "KL Rahul",
          "familyName": null,
          "otherNames": null
        },
        "dateOfBirth": null,
        "gender": null,
        "bloodGroup": null,
        "mobileNumber": "9628624667",
        "altContactNumber": null,
        "email": "rahul@gmail.com",
        "address": [
          {
            "id": "d4a6f321-3b56-45ec-aa71-191d7b2ad86c",
            "clientReferenceId": null,
            "individualId": "f6db2008-4c9d-42ce-8e7c-7761952b74fd",
            "tenantId": "kl",
            "doorNo": "",
            "latitude": 0,
            "longitude": 0,
            "locationAccuracy": 0,
            "type": "PERMANENT",
            "addressLine1": "Telangana",
            "addressLine2": "dgdfsg",
            "landmark": null,
            "city": "Kondapur",
            "pincode": "500084",
            "buildingName": "",
            "street": "Techies elite co-livin PG",
            "locality": null,
            "ward": null,
            "isDeleted": false,
            "auditDetails": {
              "createdBy": "a9597a93-4e38-49a8-8819-dd8f20bb1f91",
              "lastModifiedBy": "a9597a93-4e38-49a8-8819-dd8f20bb1f91",
              "createdTime": 1746773843205,
              "lastModifiedTime": 1746773843205
            }
          }
        ],
        "fatherName": null,
        "husbandName": null,
        "relationship": null,
        "identifiers": [
          {
            "id": "45d991da-f4bb-4a68-99b5-cd1898d2eb20",
            "clientReferenceId": null,
            "individualId": "f6db2008-4c9d-42ce-8e7c-7761952b74fd",
            "identifierType": "PAN_CARD",
            "identifierId": "********************************c290",
            "isDeleted": false,
            "auditDetails": {
              "createdBy": "a9597a93-4e38-49a8-8819-dd8f20bb1f91",
              "lastModifiedBy": "a9597a93-4e38-49a8-8819-dd8f20bb1f91",
              "createdTime": 1746773843205,
              "lastModifiedTime": 1746773843205
            }
          }
        ],
        "skills": [],
        "photo": null,
        "additionalFields": {
          "schema": null,
          "version": null,
          "fields": [
            {
              "key": "userType",
              "value": "LITIGANT"
            },
            {
              "key": "userTypeDetail",
              "value": "{\"code\": \"LITIGANT\", \"name\": \"LITIGANT_TEXT\", \"role\": [\"ADVOCATE_VIEWER\", \"APPLICATION_CREATOR\", \"APPLICATION_VIEWER\", \"BAIL_BOND_CREATOR\", \"BAIL_BOND_EDITOR\", \"BAIL_BOND_VIEWER\", \"CASE_CREATOR\", \"CASE_EDITOR\", \"CASE_VIEWER\", \"EVIDENCE_CREATOR\", \"EVIDENCE_EDITOR\", \"EVIDENCE_VIEWER\", \"HEARING_ACCEPTOR\", \"HEARING_VIEWER\", \"ORDER_VIEWER\", \"PENDING_TASK_CREATOR\", \"SUBMISSION_CREATOR\", \"SUBMISSION_DELETE\", \"SUBMISSION_RESPONDER\", \"TASK_VIEWER\"], \"subText\": \"LITIGANT_SUB_TEXT\", \"isVerified\": false, \"showBarDetails\": false}"
            },
            {
              "key": "termsAndCondition",
              "value": "true"
            },
            {
              "key": "identifierIdDetails",
              "value": "{\"fileStoreId\":\"62837931-b64e-4784-bde1-8e7da8cbc290\",\"filename\":\"Screenshot from 2025-04-22 19-17-26.png\"}"
            }
          ]
        },
        "isDeleted": false,
        "rowVersion": 1,
        "auditDetails": {
          "createdBy": "a9597a93-4e38-49a8-8819-dd8f20bb1f91",
          "lastModifiedBy": "a9597a93-4e38-49a8-8819-dd8f20bb1f91",
          "createdTime": 1746773843204,
          "lastModifiedTime": 1746773843204
        },
        "clientAuditDetails": {
          "createdBy": null,
          "lastModifiedBy": null,
          "createdTime": 0,
          "lastModifiedTime": 0
        },
        "isSystemUser": true,
        "isSystemUserActive": true,
        "userDetails": {
          "username": "9628624667",
          "password": null,
          "tenantId": "kl",
          "roles": [
            {
              "name": "ADVOCATE_VIEWER",
              "code": "ADVOCATE_VIEWER",
              "description": null,
              "tenantId": "kl"
            },
            {
              "name": "APPLICATION_CREATOR",
              "code": "APPLICATION_CREATOR",
              "description": null,
              "tenantId": "kl"
            },
            {
              "name": "APPLICATION_VIEWER",
              "code": "APPLICATION_VIEWER",
              "description": null,
              "tenantId": "kl"
            },
            {
              "name": "BAIL_BOND_CREATOR",
              "code": "BAIL_BOND_CREATOR",
              "description": null,
              "tenantId": "kl"
            },
            {
              "name": "BAIL_BOND_EDITOR",
              "code": "BAIL_BOND_EDITOR",
              "description": null,
              "tenantId": "kl"
            },
            {
              "name": "BAIL_BOND_VIEWER",
              "code": "BAIL_BOND_VIEWER",
              "description": null,
              "tenantId": "kl"
            },
            {
              "name": "CASE_CREATOR",
              "code": "CASE_CREATOR",
              "description": null,
              "tenantId": "kl"
            },
            {
              "name": "CASE_EDITOR",
              "code": "CASE_EDITOR",
              "description": null,
              "tenantId": "kl"
            },
            {
              "name": "CASE_VIEWER",
              "code": "CASE_VIEWER",
              "description": null,
              "tenantId": "kl"
            },
            {
              "name": "Citizen",
              "code": "CITIZEN",
              "description": null,
              "tenantId": "kl"
            },
            {
              "name": "EVIDENCE_CREATOR",
              "code": "EVIDENCE_CREATOR",
              "description": null,
              "tenantId": "kl"
            },
            {
              "name": "EVIDENCE_EDITOR",
              "code": "EVIDENCE_EDITOR",
              "description": null,
              "tenantId": "kl"
            },
            {
              "name": "EVIDENCE_VIEWER",
              "code": "EVIDENCE_VIEWER",
              "description": null,
              "tenantId": "kl"
            },
            {
              "name": "HEARING_ACCEPTOR",
              "code": "HEARING_ACCEPTOR",
              "description": null,
              "tenantId": "kl"
            },
            {
              "name": "HEARING_VIEWER",
              "code": "HEARING_VIEWER",
              "description": null,
              "tenantId": "kl"
            },
            {
              "name": "ORDER_VIEWER",
              "code": "ORDER_VIEWER",
              "description": null,
              "tenantId": "kl"
            },
            {
              "name": "PENDING_TASK_CREATOR",
              "code": "PENDING_TASK_CREATOR",
              "description": null,
              "tenantId": "kl"
            },
            {
              "name": "SUBMISSION_CREATOR",
              "code": "SUBMISSION_CREATOR",
              "description": null,
              "tenantId": "kl"
            },
            {
              "name": "SUBMISSION_DELETE",
              "code": "SUBMISSION_DELETE",
              "description": null,
              "tenantId": "kl"
            },
            {
              "name": "SUBMISSION_RESPONDER",
              "code": "SUBMISSION_RESPONDER",
              "description": null,
              "tenantId": "kl"
            },
            {
              "name": "TASK_VIEWER",
              "code": "TASK_VIEWER",
              "description": null,
              "tenantId": "kl"
            }
          ],
          "type": "CITIZEN"
        }
      }
    ]
  },
  "litigentIndividualId": "IND-2025-05-09-000305",
  "litigentuserinfo": {
    "id": 1978,
    "userName": "9628624667",
    "salutation": null,
    "name": "KL Rahul  ",
    "gender": null,
    "mobileNumber": "9628624667",
    "emailId": "rahul@gmail.com",
    "altContactNumber": null,
    "pan": null,
    "aadhaarNumber": null,
    "permanentAddress": null,
    "permanentCity": null,
    "permanentPinCode": null,
    "correspondenceAddress": null,
    "correspondenceCity": null,
    "correspondencePinCode": null,
    "alternatemobilenumber": null,
    "active": true,
    "locale": null,
    "type": "CITIZEN",
    "accountLocked": false,
    "accountLockedDate": 0,
    "fatherOrHusbandName": null,
    "relationship": null,
    "signature": null,
    "bloodGroup": null,
    "photo": null,
    "identificationMark": null,
    "createdBy": 0,
    "lastModifiedBy": 1978,
    "tenantId": "kl",
    "roles": [
      {
        "code": "CASE_VIEWER",
        "name": "CASE_VIEWER",
        "tenantId": "kl"
      },
      {
        "code": "HEARING_VIEWER",
        "name": "HEARING_VIEWER",
        "tenantId": "kl"
      },
      {
        "code": "CITIZEN",
        "name": "Citizen",
        "tenantId": "kl"
      },
      {
        "code": "BAIL_BOND_CREATOR",
        "name": "BAIL_BOND_CREATOR",
        "tenantId": "kl"
      },
      {
        "code": "BAIL_BOND_VIEWER",
        "name": "BAIL_BOND_VIEWER",
        "tenantId": "kl"
      },
      {
        "code": "APPLICATION_CREATOR",
        "name": "APPLICATION_CREATOR",
        "tenantId": "kl"
      },
      {
        "code": "EVIDENCE_CREATOR",
        "name": "EVIDENCE_CREATOR",
        "tenantId": "kl"
      },
      {
        "code": "EVIDENCE_EDITOR",
        "name": "EVIDENCE_EDITOR",
        "tenantId": "kl"
      },
      {
        "code": "SUBMISSION_DELETE",
        "name": "SUBMISSION_DELETE",
        "tenantId": "kl"
      },
      {
        "code": "BAIL_BOND_EDITOR",
        "name": "BAIL_BOND_EDITOR",
        "tenantId": "kl"
      },
      {
        "code": "HEARING_ACCEPTOR",
        "name": "HEARING_ACCEPTOR",
        "tenantId": "kl"
      },
      {
        "code": "ORDER_VIEWER",
        "name": "ORDER_VIEWER",
        "tenantId": "kl"
      },
      {
        "code": "SUBMISSION_RESPONDER",
        "name": "SUBMISSION_RESPONDER",
        "tenantId": "kl"
      },
      {
        "code": "CASE_EDITOR",
        "name": "CASE_EDITOR",
        "tenantId": "kl"
      },
      {
        "code": "EVIDENCE_VIEWER",
        "name": "EVIDENCE_VIEWER",
        "tenantId": "kl"
      },
      {
        "code": "ADVOCATE_VIEWER",
        "name": "ADVOCATE_VIEWER",
        "tenantId": "kl"
      },
      {
        "code": "APPLICATION_VIEWER",
        "name": "APPLICATION_VIEWER",
        "tenantId": "kl"
      },
      {
        "code": "SUBMISSION_CREATOR",
        "name": "SUBMISSION_CREATOR",
        "tenantId": "kl"
      },
      {
        "code": "TASK_VIEWER",
        "name": "TASK_VIEWER",
        "tenantId": "kl"
      },
      {
        "code": "CASE_CREATOR",
        "name": "CASE_CREATOR",
        "tenantId": "kl"
      },
      {
        "code": "PENDING_TASK_CREATOR",
        "name": "PENDING_TASK_CREATOR",
        "tenantId": "kl"
      }
    ],
    "uuid": "a9597a93-4e38-49a8-8819-dd8f20bb1f91",
    "createdDate": "09-05-2025 12:26:28",
    "lastModifiedDate": "09-05-2025 12:27:23",
    "dob": null,
    "pwdExpiryDate": "07-08-2025 12:26:28"
  },
  "UATfilestore1": {
    "case.cheque": "a359d3d8-faf1-4501-b3e1-d5a6ff82d453",
    "case.cheque.returnmemo": "a359d3d8-faf1-4501-b3e1-d5a6ff82d453",
    "case.liabilityproof": "a359d3d8-faf1-4501-b3e1-d5a6ff82d453",
    "case.demandnotice": "a359d3d8-faf1-4501-b3e1-d5a6ff82d453",
    "case.demandnotice.proof": "a359d3d8-faf1-4501-b3e1-d5a6ff82d453",
    "case.demandnotice.serviceproof": "a359d3d8-faf1-4501-b3e1-d5a6ff82d453",
    "VAKALATNAMA_DOC": "a359d3d8-faf1-4501-b3e1-d5a6ff82d453",
    "case.affidavit.223bnss": "a359d3d8-faf1-4501-b3e1-d5a6ff82d453",
    "COMPLAINANT_ID_PROOF": "a359d3d8-faf1-4501-b3e1-d5a6ff82d453",
    "case.affidavit.225bnss": "a359d3d8-faf1-4501-b3e1-d5a6ff82d453",
    "image/png": "a359d3d8-faf1-4501-b3e1-d5a6ff82d453",
    "orderTitle": "a359d3d8-faf1-4501-b3e1-d5a6ff82d453",
    "application": "a359d3d8-faf1-4501-b3e1-d5a6ff82d453",
    "case.complaint.signed": "8f2c8c90-6e7a-47d2-99d5-6e6d94dbd323"
  },
  "UATfilestore2-dev": {
    "case.cheque": "2efe9766-9190-48f1-9442-91a670321e1f",
    "case.cheque.returnmemo": "2efe9766-9190-48f1-9442-91a670321e1f",
    "case.liabilityproof": "2efe9766-9190-48f1-9442-91a670321e1f",
    "case.demandnotice": "2efe9766-9190-48f1-9442-91a670321e1f",
    "case.demandnotice.proof": "2efe9766-9190-48f1-9442-91a670321e1f",
    "case.demandnotice.serviceproof": "2efe9766-9190-48f1-9442-91a670321e1f",
    "VAKALATNAMA_DOC": "2efe9766-9190-48f1-9442-91a670321e1f",
    "case.affidavit.223bnss": "2efe9766-9190-48f1-9442-91a670321e1f",
    "COMPLAINANT_ID_PROOF": "2efe9766-9190-48f1-9442-91a670321e1f",
    "case.affidavit.225bnss": "2efe9766-9190-48f1-9442-91a670321e1f",
    "orderTitle": "2efe9766-9190-48f1-9442-91a670321e1f5",
    "application": "2efe9766-9190-48f1-9442-91a670321e1f",
    "image/png": "2efe9766-9190-48f1-9442-91a670321e1f",
    "case.complaint.signed": "0a036a96-55fe-47e8-849c-15bf53897cae"
  },
  "UATfilestore": {
    "case.cheque": "303153cb-7117-4c52-924d-7daade1fb40e",
    "case.cheque.returnmemo": "abbe61b4-9998-45dd-a640-0fb21d34d79e",
    "case.liabilityproof": "ca57727d-71d0-4943-b083-215b1d71e99f",
    "case.demandnotice": "812000fc-a947-4941-a841-9c3e36d312ca",
    "case.demandnotice.proof": "1290b4c8-a8f0-4675-af80-d4903ab13d71",
    "case.demandnotice.serviceproof": "5ee759f0-9974-4946-b020-6dd8d523da14",
    "VAKALATNAMA_DOC": "ba1ffab5-b508-4cea-b0e7-ecfcbd7d6056",
    "case.affidavit.223bnss": "2e1c7855-e7bb-4243-ad73-2cffc502b0fe",
    "COMPLAINANT_ID_PROOF": "b7b06ce0-c41b-431c-8825-06f9f92fea3f",
    "case.affidavit.225bnss": "ab09c39e-c5b0-487e-b50e-6de9801980c0",
    "orderTitle": "f700e0c3-b6d2-4beb-bb07-a748aab5ca35",
    "application": "f700e0c3-b6d2-4beb-bb07-a748aab5ca35",
    "image/png": "76bf63b2-fd6f-4c2e-a55a-a9778df19233",
    "case.complaint.signed": "8014e2b4-f963-4786-bcd3-26371a76bc59"
  },
  "fetchCaseBundlePdfResponse": {
    "filePath": "/home/bhlp0121/Desktop/Qa-Automation/Case create/tests/caseComplaintDetails.pdf"
  },
  "advocateidproof": "faefafd2-24fc-4c63-8681-d9df33a9d253",
  "advocateusername": "AdvocateOne",
  "advocatebarregistration": "12345679999999999999",
  "citizenAuthToken": "5fff054f-955d-446a-a86c-dc3b5facceeb",
  "citizenUserInfo": {
    "id": 1181,
    "uuid": "5ba50f9a-56eb-4bee-8ae3-ee90dfb59c0f",
    "userName": "6303338642",
    "name": "Maruthi  ch",
    "mobileNumber": "6303338642",
    "emailId": "marruthi@gmail.com",
    "locale": null,
    "type": "CITIZEN",
    "roles": [
      {
        "name": "USER_REGISTER",
        "code": "USER_REGISTER",
        "tenantId": "kl"
      },
      {
        "name": "CASE_VIEWER",
        "code": "CASE_VIEWER",
        "tenantId": "kl"
      },
      {
        "name": "HEARING_VIEWER",
        "code": "HEARING_VIEWER",
        "tenantId": "kl"
      },
      {
        "name": "Citizen",
        "code": "CITIZEN",
        "tenantId": "kl"
      },
      {
        "name": "BAIL_BOND_CREATOR",
        "code": "BAIL_BOND_CREATOR",
        "tenantId": "kl"
      },
      {
        "name": "ADVOCATE_ROLE",
        "code": "ADVOCATE_ROLE",
        "tenantId": "kl"
      },
      {
        "name": "BAIL_BOND_VIEWER",
        "code": "BAIL_BOND_VIEWER",
        "tenantId": "kl"
      },
      {
        "name": "APPLICATION_CREATOR",
        "code": "APPLICATION_CREATOR",
        "tenantId": "kl"
      },
      {
        "name": "EVIDENCE_CREATOR",
        "code": "EVIDENCE_CREATOR",
        "tenantId": "kl"
      },
      {
        "name": "EVIDENCE_EDITOR",
        "code": "EVIDENCE_EDITOR",
        "tenantId": "kl"
      },
      {
        "name": "SUBMISSION_DELETE",
        "code": "SUBMISSION_DELETE",
        "tenantId": "kl"
      },
      {
        "name": "BAIL_BOND_EDITOR",
        "code": "BAIL_BOND_EDITOR",
        "tenantId": "kl"
      },
      {
        "name": "HEARING_ACCEPTOR",
        "code": "HEARING_ACCEPTOR",
        "tenantId": "kl"
      },
      {
        "name": "ORDER_VIEWER",
        "code": "ORDER_VIEWER",
        "tenantId": "kl"
      },
      {
        "name": "SUBMISSION_RESPONDER",
        "code": "SUBMISSION_RESPONDER",
        "tenantId": "kl"
      },
      {
        "name": "CASE_EDITOR",
        "code": "CASE_EDITOR",
        "tenantId": "kl"
      },
      {
        "name": "EVIDENCE_VIEWER",
        "code": "EVIDENCE_VIEWER",
        "tenantId": "kl"
      },
      {
        "name": "ADVOCATE_VIEWER",
        "code": "ADVOCATE_VIEWER",
        "tenantId": "kl"
      },
      {
        "name": "APPLICATION_VIEWER",
        "code": "APPLICATION_VIEWER",
        "tenantId": "kl"
      },
      {
        "name": "SUBMISSION_CREATOR",
        "code": "SUBMISSION_CREATOR",
        "tenantId": "kl"
      },
      {
        "name": "TASK_VIEWER",
        "code": "TASK_VIEWER",
        "tenantId": "kl"
      },
      {
        "name": "ADVOCATE_APPLICATION_VIEWER",
        "code": "ADVOCATE_APPLICATION_VIEWER",
        "tenantId": "kl"
      },
      {
        "name": "CASE_CREATOR",
        "code": "CASE_CREATOR",
        "tenantId": "kl"
      },
      {
        "name": "PENDING_TASK_CREATOR",
        "code": "PENDING_TASK_CREATOR",
        "tenantId": "kl"
      }
    ],
    "active": true,
    "tenantId": "kl",
    "permanentCity": null
  }
}